cliutil/Arguments.py
cliutil/Configuration.py
cliutil/Permissions.py
cliutil/Questions.py
cliutil/Selections.py
cliutil/__init__.py
cliutil-0.1.2.dist-info/LICENSE
cliutil-0.1.2.dist-info/METADATA
cliutil-0.1.2.dist-info/WHEEL
cliutil-0.1.2.dist-info/top_level.txt
cliutil-0.1.2.dist-info/RECORD
